{
  "bill_id": "117-s-2747",
  "congress": 117,
  "bill_type": "s",
  "bill_number": 2747,
  "title": "To expand Americans\u2019 access to the ballot box and reduce the influence of big money in politics, and for other purposes.",
  "short_title": "Freedom to Vote Act",
  "sponsor": "Ms. Klobuchar",
  "introduced_date": "Sept-em-be",
  "latest_action": null,
  "policy_area": null,
  "subjects": [],
  "summary_text": null,
  "centrality_score": null,
  "match_locations": {},
  "tier": "A",
  "stream": "legislation",
  "topic": "redistricting",
  "versions_available": [
    {
      "package_id": "BILLS-117s2747pcs",
      "version_code": "pcs",
      "date_issued": "Sept-em-be"
    }
  ],
  "canonical_version": {
    "package_id": "BILLS-117s2747pcs",
    "version_code": "pcs",
    "date_issued": "Sept-em-be"
  },
  "actions": [],
  "cosponsors": [],
  "_metadata_sources": {
    "xml": "govinfo bulk-data (unauthenticated)",
    "congress_gov_enriched": false
  }
}
